caddy/__init__.py
caddy/api.py
caddy/base.py
caddy/tools.py
caddy_python-0.0.54.dist-info/METADATA
caddy_python-0.0.54.dist-info/WHEEL
caddy_python-0.0.54.dist-info/top_level.txt
caddy_python-0.0.54.dist-info/RECORD
