Metadata-Version: 2.1
Name: caddy-python
Version: 0.0.54
Summary: Python SDK for Caddy
Author: Caddy
Requires-Python: >=3.6
Requires-Dist: requests
